LICENSE.txt
MANIFEST.in
README.rst
long_description.rst
readme.rst
requirements.txt
setup.cfg
setup.py
canbeAny/__init__.py
canbeAny/module1.py
canbeAny/module2.py
canbeAny/zzz_manual_install.py
canbeAny.egg-info/PKG-INFO
canbeAny.egg-info/SOURCES.txt
canbeAny.egg-info/dependency_links.txt
canbeAny.egg-info/requires.txt
canbeAny.egg-info/top_level.txt
canbeAny/packages/__init__.py
canbeAny/packages/subpackage1/__init__.py
canbeAny/packages/subpackage1/module11.py
canbeAny/packages/subpackage1/module12.py
canbeAny/packages/subpackage2/__init__.py
canbeAny/packages/subpackage2/module21.py
canbeAny/packages/subpackage2/module22.py